Notesh-0.8.0.data/data/share/applications/Notesh.desktop
notesh/__init__.py
notesh/command_line.py
notesh/default_bindings.toml
notesh/main.css
notesh/main.py
notesh/play_area.py
notesh/utils.py
notesh/drawables/__init__.py
notesh/drawables/box.py
notesh/drawables/drawable.py
notesh/drawables/sticknote.py
notesh/widgets/__init__.py
notesh/widgets/color_picker.py
notesh/widgets/focusable_footer.py
notesh/widgets/multiline_input.py
notesh/widgets/sidebar.py
notesh/widgets/sidebar_left.py
Notesh-0.8.0.dist-info/LICENSE
Notesh-0.8.0.dist-info/METADATA
Notesh-0.8.0.dist-info/WHEEL
Notesh-0.8.0.dist-info/entry_points.txt
Notesh-0.8.0.dist-info/top_level.txt
Notesh-0.8.0.dist-info/RECORD
