Metadata-Version: 2.1
Name: Notesh
Version: 0.8.0
Summary: NoteSH: A fully functional sticky notes App in your Terminal!
Home-page: http://github.com/Cvaniak/Notesh
Author: Cvaniak
Author-email: igna.cwaniak@gmail.com
License: MIT
Requires-Python: >=3.7, <4
License-File: LICENSE
Requires-Dist: textual ==0.37.1
Requires-Dist: tomli ==2.0.1
Requires-Dist: hoptex ==0.2.0
